mrcregexhelper/__init__.py
mrcregexhelper-1.1.dist-info/METADATA
mrcregexhelper-1.1.dist-info/WHEEL
mrcregexhelper-1.1.dist-info/top_level.txt
mrcregexhelper-1.1.dist-info/RECORD
