Metadata-Version: 2.1
Name: mrcregexhelper
Version: 1.1
Summary: Regex utility
Home-page: UNKNOWN
Author: Mr. Cooper
Author-email: varshitha.dasari@mrcooper.com
License: MIT
Platform: UNKNOWN
Requires-Dist: pandas
Requires-Dist: requests
Requires-Dist: numpy
Requires-Dist: fuzzywuzzy
Requires-Dist: python-Levenshtein ; sys_platform == "darwin"
